ChangeLog
FixedPoint.py
LICENSE
MANIFEST.in
Makefile
README.md
ToDo
demo.py
setup.py
spfpm.egg-info/PKG-INFO
spfpm.egg-info/SOURCES.txt
spfpm.egg-info/dependency_links.txt
spfpm.egg-info/top_level.txt
test/testFixedPoint.py