Metadata-Version: 2.1
Name: spfpm
Version: 1.6
Summary: Tools for arithmetic on fixed-point (binary) numbers
Home-page: https://github.com/rwpenney/spfpm
Author: RW Penney
Author-email: rwpenney@users.sourceforge.net
License: PSF Python License
Keywords: arithmetic,fixed-point,trigonometry,arbitrary precision
Platform: UNKNOWN
Classifier: Programming Language :: Python :: 3
Classifier: Intended Audience :: Science/Research
Classifier: Operating System :: OS Independent
Classifier: Topic :: Scientific/Engineering :: Mathematics
Classifier: Topic :: Software Development :: Embedded Systems
License-File: LICENSE
